mylib/__init__.py
mylib/_version.py
pyproject_tmpl-0.1.0.dist-info/METADATA
pyproject_tmpl-0.1.0.dist-info/WHEEL
pyproject_tmpl-0.1.0.dist-info/top_level.txt
pyproject_tmpl-0.1.0.dist-info/RECORD
