Metadata-Version: 2.4
Name: pyproject-tmpl
Version: 0.1.0
Summary: template python project with necessary configurations
Author-email: xdewx <present150608@sina.com>
Requires-Python: >=3.10
